kchd/__init__.py
kchd/app.py
kchd/controllers/__init__.py
kchd/controllers/astmetad.py
kchd/controllers/astprocd.py
kchd/controllers/astwifid.py
kchd/controllers/controller.py
kchd/controllers/request.py
kchd/controllers/system_status.py
kchd/driver/__init__.py
kchd/driver/driver.py
kchd/driver/gpio.py
kchd/driver/mock.py
kchd/hardware.py
kchd/types.py
kchd-0.4.1.dist-info/entry_points.txt
kchd-0.4.1.dist-info/LICENSE
kchd-0.4.1.dist-info/WHEEL
kchd-0.4.1.dist-info/METADATA
kchd-0.4.1.dist-info/RECORD
