Metadata-Version: 2.1
Name: kchd
Version: 0.4.1
Summary: KCH LED Daemon
Author: Dan Trickey
Author-email: dtrickey@studentrobotics.org
Requires-Python: >=3.8,<4.0
Classifier: Programming Language :: Python :: 3
Classifier: Programming Language :: Python :: 3.8
Classifier: Programming Language :: Python :: 3.9
Classifier: Programming Language :: Python :: 3.10
Classifier: Programming Language :: Python :: 3.11
Requires-Dist: astoria (>=0.11.1,<0.12.0)
